README.md
setup.cfg
setup.py
aestar/aesfile.py
aestar/chio.py
aestar/db.py
aestar/main.py
aestar.egg-info/PKG-INFO
aestar.egg-info/SOURCES.txt
aestar.egg-info/dependency_links.txt
aestar.egg-info/requires.txt
aestar.egg-info/top_level.txt